reyworm/__init__.py
reyworm/rall.py
reyworm/rbase.py
reyworm/rcommon/__init__.py
reyworm/rcommon/rcalendar.py
reyworm/rcommon/rtranslate.py
reyworm/rfinance/__init__.py
reyworm/rfinance/rsina.py
reyworm/rmedia/__init__.py
reyworm/rmedia/rdouban.py
reyworm/rmedia/rtoutiao.py
reyworm/rmedia/rweibo.py
reyworm-1.0.34.dist-info/METADATA
reyworm-1.0.34.dist-info/WHEEL
reyworm-1.0.34.dist-info/licenses/LICENSE
reyworm-1.0.34.dist-info/RECORD
