Metadata-Version: 2.4
Name: reyworm
Version: 1.0.34
Summary: Worm method set.
Project-URL: homepage, https://github.com/reyxbo/reyworm/
Author-email: Rey <reyxbo@163.com>
License: Copyright 2025 ReyXBo
License-File: LICENSE
Keywords: rey,reyxbo,worm
Requires-Python: >=3.12
Requires-Dist: fake-useragent
Requires-Dist: reykit
Requires-Dist: selenium
